multicontentsmanager/__init__.py
multicontentsmanager/_version.py
multicontentsmanager/absolute.py
multicontentsmanager/extension.py
multicontentsmanager/handlers.py
multicontentsmanager/metacontentsmanager.py
multicontentsmanager/tests/__init__.py
multicontentsmanager/tests/test_extension.py
multicontentsmanager/tests/test_handlers.py
multicontentsmanager/tests/test_init.py
multicontentsmanager-0.0.1.data/data/etc/jupyter/jupyter_notebook_config.d/multicontentsmanager.json
multicontentsmanager-0.0.1.data/data/share/jupyter/lab/extensions/multicontentsmanager-0.0.1.tgz
multicontentsmanager-0.0.1.dist-info/LICENSE
multicontentsmanager-0.0.1.dist-info/METADATA
multicontentsmanager-0.0.1.dist-info/WHEEL
multicontentsmanager-0.0.1.dist-info/top_level.txt
multicontentsmanager-0.0.1.dist-info/RECORD
