Metadata-Version: 2.1
Name: multicontentsmanager
Version: 0.0.1
Summary: Automatically version notebooks from JupyterLab
Home-page: https://github.com/timkpaine/multicontentsmanager
Author: Tim Paine
Author-email: t.paine154@gmail.com
License: Apache 2.0
Keywords: jupyter jupyterlab
Platform: UNKNOWN
Classifier: Development Status :: 3 - Alpha
Classifier: Programming Language :: Python :: 2
Classifier: Programming Language :: Python :: 2.7
Classifier: Programming Language :: Python :: 3
Classifier: Programming Language :: Python :: 3.6
Classifier: Programming Language :: Python :: 3.7
Classifier: Programming Language :: Python :: 3.8
Classifier: Framework :: Jupyter
Requires-Dist: GitPython (>=2.1.11)
Requires-Dist: jupyterlab (>=1.0.0)
Provides-Extra: dev
Requires-Dist: pytest ; extra == 'dev'
Requires-Dist: pytest-cov ; extra == 'dev'
Requires-Dist: pylint ; extra == 'dev'
Requires-Dist: flake8 ; extra == 'dev'
Requires-Dist: bumpversion ; extra == 'dev'
Requires-Dist: mock ; extra == 'dev'
Requires-Dist: codecov ; extra == 'dev'
Requires-Dist: autopep8 ; extra == 'dev'
